{
  "title": "Sheet Pan Salmon with Vegetables",
  "author": {
    "name": "The Mediterranean Dish"
  },
  "tasks": [
    {
      "id": "chain_1/step_1",
      "name": "Prepare",
      "canonical_verb": "free_text",
      "duration_min": null,
      "planned_min": null,
      "requires_driver": true,
      "self_running_after_start": false,
      "hold_window_minutes": null,
      "temporal_flexibility": "serve_immediate",
      "inputs": [],
      "outputs": [],
      "equipment": [],
      "edges": [],
      "_meta": {
        "verb_confidence": "low",
        "verb_source": "default",
        "duration_source": null,
        "duration_approx": false
      }
    },
    {
      "id": "chain_1/step_2",
      "name": "Heat your oven to 450°F.",
      "canonical_verb": "preheat_oven",
      "duration_min": null,
      "planned_min": 12,
      "requires_driver": false,
      "self_running_after_start": true,
      "hold_window_minutes": 0,
      "temporal_flexibility": "serve_immediate",
      "inputs": [],
      "outputs": [],
      "equipment": [
        "oven"
      ],
      "edges": [
        {
          "from": "chain_1/step_1",
          "to": "chain_1/step_2",
          "type": "FS",
          "constraint": "RIGID"
        }
      ],
      "_meta": {
        "verb_confidence": "high",
        "verb_source": "verb_pattern",
        "duration_source": null,
        "duration_approx": false
      },
      "temperature": {
        "value": 450,
        "unit": "F"
      }
    },
    {
      "id": "chain_2/step_1",
      "name": "Make the spice blend",
      "canonical_verb": "free_text",
      "duration_min": null,
      "planned_min": null,
      "requires_driver": true,
      "self_running_after_start": false,
      "hold_window_minutes": null,
      "temporal_flexibility": "serve_immediate",
      "inputs": [],
      "outputs": [],
      "equipment": [],
      "edges": [],
      "_meta": {
        "verb_confidence": "low",
        "verb_source": "default",
        "duration_source": null,
        "duration_approx": false
      }
    },
    {
      "id": "chain_2/step_2",
      "name": "Combine paprika, baharat, 1¼ teaspoon salt, and generous pepper in a small bowl.",
      "canonical_verb": "season",
      "duration_min": null,
      "planned_min": 1,
      "requires_driver": true,
      "self_running_after_start": false,
      "hold_window_minutes": 0,
      "temporal_flexibility": "serve_immediate",
      "inputs": [
        "salt",
        "pepper"
      ],
      "outputs": [],
      "equipment": [
        "bowl"
      ],
      "edges": [
        {
          "from": "chain_2/step_1",
          "to": "chain_2/step_2",
          "type": "FS",
          "constraint": "RIGID"
        }
      ],
      "_meta": {
        "verb_confidence": "high",
        "verb_source": "verb_pattern",
        "duration_source": null,
        "duration_approx": false
      }
    },
    {
      "id": "chain_3/step_1",
      "name": "Ready the vegetables",
      "canonical_verb": "free_text",
      "duration_min": null,
      "planned_min": null,
      "requires_driver": true,
      "self_running_after_start": false,
      "hold_window_minutes": null,
      "temporal_flexibility": "serve_immediate",
      "inputs": [],
      "outputs": [],
      "equipment": [],
      "edges": [],
      "_meta": {
        "verb_confidence": "low",
        "verb_source": "default",
        "duration_source": null,
        "duration_approx": false
      }
    },
    {
      "id": "chain_3/step_2",
      "name": "Remove cauliflower leaves and core",
      "canonical_verb": "free_text",
      "duration_min": null,
      "planned_min": null,
      "requires_driver": true,
      "self_running_after_start": false,
      "hold_window_minutes": null,
      "temporal_flexibility": "serve_immediate",
      "inputs": [],
      "outputs": [],
      "equipment": [],
      "edges": [
        {
          "from": "chain_3/step_1",
          "to": "chain_3/step_2",
          "type": "FS",
          "constraint": "RIGID"
        }
      ],
      "_meta": {
        "verb_confidence": "low",
        "verb_source": "default",
        "duration_source": null,
        "duration_approx": false
      }
    },
    {
      "id": "chain_3/step_3",
      "name": "cut florets into bite-sized pieces (about 6 cups total)",
      "canonical_verb": "chop",
      "duration_min": null,
      "planned_min": 2,
      "requires_driver": true,
      "self_running_after_start": false,
      "hold_window_minutes": 10080,
      "temporal_flexibility": "hold_days",
      "inputs": [],
      "outputs": [],
      "equipment": [],
      "edges": [
        {
          "from": "chain_3/step_2",
          "to": "chain_3/step_3",
          "type": "FS",
          "constraint": "RIGID"
        }
      ],
      "_meta": {
        "verb_confidence": "high",
        "verb_source": "verb_pattern",
        "duration_source": null,
        "duration_approx": false
      }
    },
    {
      "id": "chain_3/step_4",
      "name": "Slice carrots lengthwise if needed",
      "canonical_verb": "slice",
      "duration_min": null,
      "planned_min": 3,
      "requires_driver": true,
      "self_running_after_start": false,
      "hold_window_minutes": 10080,
      "temporal_flexibility": "hold_days",
      "inputs": [
        "carrot"
      ],
      "outputs": [],
      "equipment": [],
      "edges": [
        {
          "from": "chain_3/step_3",
          "to": "chain_3/step_4",
          "type": "FS",
          "constraint": "FLEXIBLE",
          "hold_window_minutes": 10080,
          "temporal_flexibility": "hold_days"
        }
      ],
      "_meta": {
        "verb_confidence": "high",
        "verb_source": "verb_pattern",
        "duration_source": null,
        "duration_approx": false
      }
    },
    {
      "id": "chain_3/step_5",
      "name": "cut diagonally into ½-inch pieces",
      "canonical_verb": "chop",
      "duration_min": null,
      "planned_min": 2,
      "requires_driver": true,
      "self_running_after_start": false,
      "hold_window_minutes": 10080,
      "temporal_flexibility": "hold_days",
      "inputs": [],
      "outputs": [],
      "equipment": [],
      "edges": [
        {
          "from": "chain_3/step_4",
          "to": "chain_3/step_5",
          "type": "FS",
          "constraint": "FLEXIBLE",
          "hold_window_minutes": 10080,
          "temporal_flexibility": "hold_days",
          "emergent_ingredient": "sliced_carrot"
        }
      ],
      "_meta": {
        "verb_confidence": "high",
        "verb_source": "verb_pattern",
        "duration_source": null,
        "duration_approx": false
      }
    },
    {
      "id": "chain_3/step_6",
      "name": "Toss vegetables with garlic, 2 tablespoons oil, and ¾ of the spice mixture in a large bowl",
      "canonical_verb": "toss",
      "duration_min": null,
      "planned_min": 1,
      "requires_driver": true,
      "self_running_after_start": false,
      "hold_window_minutes": 30,
      "temporal_flexibility": "hold_minutes",
      "inputs": [
        "garlic",
        "oil"
      ],
      "outputs": [],
      "equipment": [
        "bowl"
      ],
      "edges": [
        {
          "from": "chain_3/step_5",
          "to": "chain_3/step_6",
          "type": "FS",
          "constraint": "FLEXIBLE",
          "hold_window_minutes": 10080,
          "temporal_flexibility": "hold_days"
        }
      ],
      "_meta": {
        "verb_confidence": "medium",
        "verb_source": "pattern",
        "duration_source": null,
        "duration_approx": false
      }
    },
    {
      "id": "chain_3/step_7",
      "name": "Spread on a rimmed baking sheet in a single layer.",
      "canonical_verb": "free_text",
      "duration_min": null,
      "planned_min": null,
      "requires_driver": true,
      "self_running_after_start": false,
      "hold_window_minutes": null,
      "temporal_flexibility": "serve_immediate",
      "inputs": [],
      "outputs": [],
      "equipment": [],
      "edges": [
        {
          "from": "chain_3/step_6",
          "to": "chain_3/step_7",
          "type": "FS",
          "constraint": "FLEXIBLE",
          "hold_window_minutes": 30,
          "temporal_flexibility": "hold_minutes"
        }
      ],
      "_meta": {
        "verb_confidence": "low",
        "verb_source": "default",
        "duration_source": null,
        "duration_approx": false
      }
    },
    {
      "id": "chain_4/step_1",
      "name": "Roast vegetables",
      "canonical_verb": "roast",
      "duration_min": null,
      "planned_min": 45,
      "requires_driver": false,
      "self_running_after_start": true,
      "hold_window_minutes": 120,
      "temporal_flexibility": "hold_hours",
      "inputs": [],
      "outputs": [],
      "equipment": [],
      "edges": [],
      "_meta": {
        "verb_confidence": "high",
        "verb_source": "verb_pattern",
        "duration_source": null,
        "duration_approx": false
      }
    },
    {
      "id": "chain_4/step_2",
      "name": "Bake about 15 minutes until cauliflower starts to brown.",
      "canonical_verb": "bake",
      "duration_min": {
        "value": 15
      },
      "planned_min": 15,
      "requires_driver": false,
      "self_running_after_start": true,
      "hold_window_minutes": 60,
      "temporal_flexibility": "hold_hours",
      "inputs": [],
      "outputs": [],
      "equipment": [],
      "edges": [
        {
          "from": "chain_4/step_1",
          "to": "chain_4/step_2",
          "type": "FS",
          "constraint": "FLEXIBLE",
          "hold_window_minutes": 120,
          "temporal_flexibility": "hold_hours"
        }
      ],
      "_meta": {
        "verb_confidence": "high",
        "verb_source": "verb_pattern",
        "duration_source": "single",
        "duration_approx": true
      }
    },
    {
      "id": "chain_5/step_1",
      "name": "Prepare fish",
      "canonical_verb": "free_text",
      "duration_min": null,
      "planned_min": null,
      "requires_driver": true,
      "self_running_after_start": false,
      "hold_window_minutes": null,
      "temporal_flexibility": "serve_immediate",
      "inputs": [
        "fish"
      ],
      "outputs": [],
      "equipment": [],
      "edges": [],
      "_meta": {
        "verb_confidence": "low",
        "verb_source": "default",
        "duration_source": null,
        "duration_approx": false
      }
    },
    {
      "id": "chain_5/step_2",
      "name": "While vegetables roast, brush salmon fillets with remaining oil and sprinkle with remaining spice mixture.",
      "canonical_verb": "roast",
      "duration_min": null,
      "planned_min": 45,
      "requires_driver": false,
      "self_running_after_start": true,
      "hold_window_minutes": 120,
      "temporal_flexibility": "hold_hours",
      "inputs": [
        "salmon",
        "oil"
      ],
      "outputs": [],
      "equipment": [],
      "edges": [
        {
          "from": "chain_5/step_1",
          "to": "chain_5/step_2",
          "type": "FS",
          "constraint": "RIGID"
        }
      ],
      "_meta": {
        "verb_confidence": "high",
        "verb_source": "verb_pattern",
        "duration_source": null,
        "duration_approx": false
      }
    },
    {
      "id": "chain_6/step_1",
      "name": "Combine and finish roasting",
      "canonical_verb": "combine",
      "duration_min": null,
      "planned_min": 2,
      "requires_driver": true,
      "self_running_after_start": false,
      "hold_window_minutes": 60,
      "temporal_flexibility": "hold_hours",
      "inputs": [],
      "outputs": [],
      "equipment": [],
      "edges": [],
      "_meta": {
        "verb_confidence": "high",
        "verb_source": "verb_pattern",
        "duration_source": null,
        "duration_approx": false
      }
    },
    {
      "id": "chain_6/step_2",
      "name": "Remove the pan from the oven",
      "canonical_verb": "free_text",
      "duration_min": null,
      "planned_min": null,
      "requires_driver": true,
      "self_running_after_start": false,
      "hold_window_minutes": null,
      "temporal_flexibility": "serve_immediate",
      "inputs": [],
      "outputs": [],
      "equipment": [
        "pan",
        "oven"
      ],
      "edges": [
        {
          "from": "chain_6/step_1",
          "to": "chain_6/step_2",
          "type": "FS",
          "constraint": "FLEXIBLE",
          "hold_window_minutes": 60,
          "temporal_flexibility": "hold_hours"
        }
      ],
      "_meta": {
        "verb_confidence": "low",
        "verb_source": "default",
        "duration_source": null,
        "duration_approx": false
      }
    },
    {
      "id": "chain_6/step_3",
      "name": "Toss in olives with vegetables, move them to pan sides, and place salmon in the center",
      "canonical_verb": "toss",
      "duration_min": null,
      "planned_min": 1,
      "requires_driver": true,
      "self_running_after_start": false,
      "hold_window_minutes": 30,
      "temporal_flexibility": "hold_minutes",
      "inputs": [
        "salmon"
      ],
      "outputs": [],
      "equipment": [
        "pan"
      ],
      "edges": [
        {
          "from": "chain_6/step_2",
          "to": "chain_6/step_3",
          "type": "FS",
          "constraint": "RIGID"
        }
      ],
      "_meta": {
        "verb_confidence": "high",
        "verb_source": "verb_pattern",
        "duration_source": null,
        "duration_approx": false
      }
    },
    {
      "id": "chain_6/step_4",
      "name": "Bake 5-8 minutes until fish is opaque but still moist.",
      "canonical_verb": "bake",
      "duration_min": {
        "value": 8
      },
      "planned_min": 8,
      "requires_driver": false,
      "self_running_after_start": true,
      "hold_window_minutes": 60,
      "temporal_flexibility": "hold_hours",
      "inputs": [
        "fish"
      ],
      "outputs": [],
      "equipment": [],
      "edges": [
        {
          "from": "chain_6/step_3",
          "to": "chain_6/step_4",
          "type": "FS",
          "constraint": "FLEXIBLE",
          "hold_window_minutes": 30,
          "temporal_flexibility": "hold_minutes"
        }
      ],
      "_meta": {
        "verb_confidence": "high",
        "verb_source": "verb_pattern",
        "duration_source": "range",
        "duration_approx": true
      }
    },
    {
      "id": "chain_7/step_1",
      "name": "Serve",
      "canonical_verb": "plate",
      "duration_min": null,
      "planned_min": 2,
      "requires_driver": true,
      "self_running_after_start": false,
      "hold_window_minutes": 0,
      "temporal_flexibility": "serve_immediate",
      "inputs": [],
      "outputs": [],
      "equipment": [],
      "edges": [],
      "_meta": {
        "verb_confidence": "high",
        "verb_source": "verb_pattern",
        "duration_source": null,
        "duration_approx": false
      }
    },
    {
      "id": "chain_7/step_2",
      "name": "Squeeze half the lemon over everything",
      "canonical_verb": "free_text",
      "duration_min": null,
      "planned_min": null,
      "requires_driver": true,
      "self_running_after_start": false,
      "hold_window_minutes": null,
      "temporal_flexibility": "serve_immediate",
      "inputs": [],
      "outputs": [],
      "equipment": [],
      "edges": [
        {
          "from": "chain_7/step_1",
          "to": "chain_7/step_2",
          "type": "FS",
          "constraint": "RIGID"
        }
      ],
      "_meta": {
        "verb_confidence": "low",
        "verb_source": "default",
        "duration_source": null,
        "duration_approx": false
      }
    },
    {
      "id": "chain_7/step_3",
      "name": "Divide among plates, garnish with cilantro, and serve with remaining lemon wedges",
      "canonical_verb": "plate",
      "duration_min": null,
      "planned_min": 2,
      "requires_driver": true,
      "self_running_after_start": false,
      "hold_window_minutes": 0,
      "temporal_flexibility": "serve_immediate",
      "inputs": [],
      "outputs": [],
      "equipment": [],
      "edges": [
        {
          "from": "chain_7/step_2",
          "to": "chain_7/step_3",
          "type": "FS",
          "constraint": "RIGID"
        }
      ],
      "_meta": {
        "verb_confidence": "high",
        "verb_source": "verb_pattern",
        "duration_source": null,
        "duration_approx": false
      }
    }
  ],
  "chains": [
    {
      "id": "chain_1",
      "name": "Phase 4",
      "purpose": "Complete cooking phase 4",
      "tasks": [
        "chain_1/step_1",
        "chain_1/step_2"
      ],
      "outputs": [],
      "inputs": [],
      "temporal_marker": null,
      "parallel_with": null,
      "metadata": {
        "detected_by": "ai_task_extraction",
        "confidence": "low",
        "section_index": 3
      }
    },
    {
      "id": "chain_2",
      "name": "Phase 5",
      "purpose": "Complete cooking phase 5",
      "tasks": [
        "chain_2/step_1",
        "chain_2/step_2"
      ],
      "outputs": [],
      "inputs": [],
      "temporal_marker": null,
      "parallel_with": null,
      "metadata": {
        "detected_by": "ai_task_extraction",
        "confidence": "low",
        "section_index": 4
      }
    },
    {
      "id": "chain_3",
      "name": "Phase 6",
      "purpose": "Complete cooking phase 6",
      "tasks": [
        "chain_3/step_1",
        "chain_3/step_2",
        "chain_3/step_3",
        "chain_3/step_4",
        "chain_3/step_5",
        "chain_3/step_6",
        "chain_3/step_7"
      ],
      "outputs": [],
      "inputs": [],
      "temporal_marker": null,
      "parallel_with": null,
      "metadata": {
        "detected_by": "ai_task_extraction",
        "confidence": "low",
        "section_index": 5
      }
    },
    {
      "id": "chain_4",
      "name": "Prepare baked dish",
      "purpose": "Create baked baked dish",
      "tasks": [
        "chain_4/step_1",
        "chain_4/step_2"
      ],
      "outputs": [
        {
          "emergent_id": "e_baked_dish_001",
          "ingredient": "baked_dish",
          "state": "baked",
          "description": "baked baked dish"
        }
      ],
      "inputs": [],
      "temporal_marker": null,
      "parallel_with": null,
      "metadata": {
        "detected_by": "ai_task_extraction",
        "confidence": "medium",
        "section_index": 6
      }
    },
    {
      "id": "chain_5",
      "name": "Phase 8",
      "purpose": "Complete cooking phase 8",
      "tasks": [
        "chain_5/step_1",
        "chain_5/step_2"
      ],
      "outputs": [],
      "inputs": [],
      "temporal_marker": null,
      "parallel_with": null,
      "metadata": {
        "detected_by": "ai_task_extraction",
        "confidence": "low",
        "section_index": 7
      }
    },
    {
      "id": "chain_6",
      "name": "Bake the Dish",
      "purpose": "Bake until hot and bubbly",
      "tasks": [
        "chain_6/step_1",
        "chain_6/step_2",
        "chain_6/step_3",
        "chain_6/step_4"
      ],
      "outputs": [
        {
          "emergent_id": "e_baked_dish_002",
          "ingredient": "baked_dish",
          "state": "baked",
          "description": "baked baked dish"
        }
      ],
      "inputs": [],
      "temporal_marker": null,
      "parallel_with": null,
      "metadata": {
        "detected_by": "ai_task_extraction",
        "confidence": "high",
        "section_index": 8
      }
    },
    {
      "id": "chain_7",
      "name": "Serve",
      "purpose": "Plate and serve the dish",
      "tasks": [
        "chain_7/step_1",
        "chain_7/step_2",
        "chain_7/step_3"
      ],
      "outputs": [],
      "inputs": [],
      "temporal_marker": null,
      "parallel_with": null,
      "metadata": {
        "detected_by": "ai_task_extraction",
        "confidence": "high",
        "section_index": 9
      }
    }
  ],
  "packs_meta": {
    "parser_version": "2.0.0",
    "parsed_at": "2025-10-25T06:58:30.149Z",
    "source": "local",
    "options": {
      "autoDependencies": false,
      "smartDependencies": false,
      "roundAboutUp": true,
      "detectTaskChains": true
    }
  }
}